cleanroom/__init__.py
pandas_cleanroom-1.3.7.dist-info/licenses/LICENSE
pandas_cleanroom-1.3.7.dist-info/METADATA
pandas_cleanroom-1.3.7.dist-info/WHEEL
pandas_cleanroom-1.3.7.dist-info/top_level.txt
pandas_cleanroom-1.3.7.dist-info/RECORD
